CHANGES.txt
LICENSE.txt
MANIFEST.in
README.txt
setup.py
js/__init__.py
js.nvd3.egg-info/PKG-INFO
js.nvd3.egg-info/SOURCES.txt
js.nvd3.egg-info/dependency_links.txt
js.nvd3.egg-info/entry_points.txt
js.nvd3.egg-info/namespace_packages.txt
js.nvd3.egg-info/not-zip-safe
js.nvd3.egg-info/requires.txt
js.nvd3.egg-info/top_level.txt
js/nvd3/__init__.py
js/nvd3/test_nvd3.txt
js/nvd3/resources/nv.d3.css
js/nvd3/resources/nv.d3.js
js/nvd3/resources/nv.d3.min.css
js/nvd3/resources/nv.d3.min.js