Metadata-Version: 1.0
Name: js.nvd3
Version: 1.7.1
Summary: Fanstatic packaging of NVD3
Home-page: UNKNOWN
Author: Fanstatic Developers
Author-email: fanstatic@googlegroups.com
License: BSD
Platform: UNKNOWN
